<?xml version="1.0"?>
<opencv_storage>
<stage11>
  <maxWeakCount>6</maxWeakCount>
  <stageThreshold>-1.1749439239501953e+00</stageThreshold>
  <weakClassifiers>
    <_>
      <internalNodes>
        0 -1 3871627 -2.3797675967216492e-02</internalNodes>
      <leafValues>
        5.1999998092651367e-01 -4.5549738407135010e-01</leafValues></_>
    <_>
      <internalNodes>
        0 -1 5981422 -9.5974588475655764e-05</internalNodes>
      <leafValues>
        -7.9922389984130859e-01 3.0189779400825500e-01</leafValues></_>
    <_>
      <internalNodes>
        0 -1 5776932 -1.1783400259446353e-04</internalNodes>
      <leafValues>
        2.8833818435668945e-01 -7.8124469518661499e-01</leafValues></_>
    <_>
      <internalNodes>
        0 -1 4709311 3.6990171065554023e-04</internalNodes>
      <leafValues>
        -2.7904453873634338e-01 9.1177433729171753e-01</leafValues></_>
    <_>
      <internalNodes>
        0 -1 6129532 -3.6580064333975315e-03</internalNodes>
      <leafValues>
        -7.8142631053924561e-01 3.5409149527549744e-01</leafValues></_>
    <_>
      <internalNodes>
        0 -1 5029586 -2.8580368962138891e-04</internalNodes>
      <leafValues>
        9.2051559686660767e-01 -3.1514656543731689e-01</leafValues></_></weakClassifiers></stage11>
</opencv_storage>
